Workbook

Sheet Rain Fee
B1: Project: | C1: <insert prject name>
B2: Project Number: | C2: <insert prject name>
B4: Purchase Order (main works): | C4: <insert PO number>
B5: Purchase Order (variation 1): | C5: <insert PO number>
B6: Payment Terms: | C6: <insert number of days>
A8: Task | C8: 400 | E8: 400 | G8: 400 | I8: 320 | K8: 320 | M8: 250 | O8: 220 | Q8: 180 | S8: 180 | U8: 200 | W8: Expenses | X8: Sub Totals
C9: Rianda Mills | E9: Luke Cunningham | G9: Jessica Ward | I9: Maria McCrann | K9: Milan Wickramarachchi | M9: Amin Zarrin | O9: Samantha Nieves | Q9: Emily Felstead | S9: Holly Edmunds | U9: Danni Bailey
C10: Director & Principal Engineer | E10: Director & Principal Engineer | G10: Hydrologist and Technician | I10: Senior Engineer | K10: Senior Engineer | M10: Project Engineer | O10: Graduate Scientist | Q10: Graduate Engineer | S10: Executive Assistant | U10: Operations Coordinator
A11: Item | B11: Description | C11: Hours | D11: Fee (Exc. GST) | E11: Hours | F11: Fee (Exc. GST) | G11: Hours | H11: Fee (Exc. GST) | I11: Hours | J11: Fee (Exc. GST) | K11: Hours | L11: Fee (Exc. GST) | M11: Hours | N11: Fee (Exc. GST) | O11: Hours | P11: Fee (Exc. GST) | Q11: Hours | R11: Fee (Exc. GST) | S11: Hours | T11: Fee (Exc. GST) | U11: Hours | V11: Fee (Exc. GST) | W11: Fee (Exc. GST) | X11: Exc. GST
B12: Phase 3.1 – Drainage and Stormwater Management Strategy (CCMA and CoGG approval)
A13: 1 | B13: Review of existing strategies and background reports | D13: =C13*C$8 | F13: =E13*E$8 | H13: =G13*G$8 | J13: =I13*I$8 | L13: =K13*K$8 | N13: =M13*M$8 | P13: =O13*O$8 | R13: =Q13*Q$8 | T13: =S13*S$8 | V13: =U13*U$8 | X13: =(SUM(W13+D13+F13+H13+J13+L13+N13+P13+R13+T13+V13))
A14: 2 | B14: GAP analysis and review of available LiDAR, survey, aerial imagery, and existing infrastructure | D14: =C14*C$8 | F14: =E14*E$8 | H14: =G14*G$8 | J14: =I14*I$8 | L14: =K14*K$8 | N14: =M14*M$8 | P14: =O14*O$8 | R14: =Q14*Q$8 | T14: =S14*S$8 | V14: =U14*U$8 | X14: =(SUM(W14+D14+F14+H14+J14+L14+N14+P14+R14+T14+V14))
A15: 3 | B15: Update Catchment Plan | D15: =C15*C$8 | F15: =E15*E$8 | H15: =G15*G$8 | J15: =I15*I$8 | L15: =K15*K$8 | N15: =M15*M$8 | P15: =O15*O$8 | R15: =Q15*Q$8 | T15: =S15*S$8 | V15: =U15*U$8 | X15: =(SUM(W15+D15+F15+H15+J15+L15+N15+P15+R15+T15+V15))
A16: 4 | B16: Review and update existing RAIN hydrological model (RORB) for existing and developed conditions, including location and sizing of retarding basins | D16: =C16*C$8 | F16: =E16*E$8 | H16: =G16*G$8 | J16: =I16*I$8 | L16: =K16*K$8 | N16: =M16*M$8 | P16: =O16*O$8 | R16: =Q16*Q$8 | T16: =S16*S$8 | V16: =U16*U$8 | X16: =(SUM(W16+D16+F16+H16+J16+L16+N16+P16+R16+T16+V16))
A17: 5 | B17: Prepare Flood Impact Assessment hydraulic model (TUFLOW) for existing and developed conditions, with climate change allowance per DPO | D17: =C17*C$8 | F17: =E17*E$8 | H17: =G17*G$8 | J17: =I17*I$8 | L17: =K17*K$8 | N17: =M17*M$8 | P17: =O17*O$8 | R17: =Q17*Q$8 | T17: =S17*S$8 | V17: =U17*U$8 | X17: =(SUM(W17+D17+F17+H17+J17+L17+N17+P17+R17+T17+V17))
A18: 6 | B18: Update MUSIC model for developed conditions to confirm stormwater treatment train meets best practice, including location and size of WSUD assets | D18: =C18*C$8 | F18: =E18*E$8 | H18: =G18*G$8 | J18: =I18*I$8 | L18: =K18*K$8 | N18: =M18*M$8 | P18: =O18*O$8 | R18: =Q18*Q$8 | T18: =S18*S$8 | V18: =U18*U$8 | X18: =(SUM(W18+D18+F18+H18+J18+L18+N18+P18+R18+T18+V18))
A19: 7 | B19: Liaise with Engineering Consultant to coordinate key utility servicing and development sequencing | D19: =C19*C$8 | F19: =E19*E$8 | H19: =G19*G$8 | J19: =I19*I$8 | L19: =K19*K$8 | N19: =M19*M$8 | P19: =O19*O$8 | R19: =Q19*Q$8 | T19: =S19*S$8 | V19: =U19*U$8 | X19: =(SUM(W19+D19+F19+H19+J19+L19+N19+P19+R19+T19+V19))
A20: 8 | B20: Develop conceptual plan for proposed drainage/waterway corridors and WSUD assets (retarding basins, sediment ponds, wetlands) | D20: =C20*C$8 | F20: =E20*E$8 | H20: =G20*G$8 | J20: =I20*I$8 | L20: =K20*K$8 | N20: =M20*M$8 | P20: =O20*O$8 | R20: =Q20*Q$8 | T20: =S20*S$8 | V20: =U20*U$8 | X20: =(SUM(W20+D20+F20+H20+J20+L20+N20+P20+R20+T20+V20))
A21: 9 | B21: Document all calculations, parameters, and outcomes in the DSMS Report | D21: =C21*C$8 | F21: =E21*E$8 | H21: =G21*G$8 | J21: =I21*I$8 | L21: =K21*K$8 | N21: =M21*M$8 | P21: =O21*O$8 | R21: =Q21*Q$8 | T21: =S21*S$8 | V21: =U21*U$8 | X21: =(SUM(W21+D21+F21+H21+J21+L21+N21+P21+R21+T21+V21))
B22: Phase 3.1 – Drainage and Stormwater Management Strategy (CCMA and CoGG approval) Subtotal | C22: =SUM(C13:C21) | D22: =SUM(D13:D21) | E22: =SUM(E13:E21) | F22: =SUM(F13:F21) | G22: =SUM(G13:G21) | H22: =SUM(H13:H21) | I22: =SUM(I13:I21) | J22: =SUM(J13:J21) | ... X22: =SUM(X13:X21)
B23: Phase 3.2 – Drainage Asset Management Plan (CoGG approval)
A24: 10 | B24: Asset register | D24: =C24*C$8 | F24: =E24*E$8 | H24: =G24*G$8 | J24: =I24*I$8 | L24: =K24*K$8 | N24: =M24*M$8 | P24: =O24*O$8 | R24: =Q24*Q$8 | T24: =S24*S$8 | V24: =U24*U$8 | X24: =(SUM(W24+D24+F24+H24+J24+L24+N24+P24+R24+T24+V24))
A25: 11 | B25: Public/private ownership delineation | D25: =C25*C$8 | F25: =E25*E$8 | H25: =G25*G$8 | J25: =I25*I$8 | L25: =K25*K$8 | N25: =M25*M$8 | P25: =O25*O$8 | R25: =Q25*Q$8 | T25: =S25*S$8 | V25: =U25*U$8 | X25: =(SUM(W25+D25+F25+H25+J25+L25+N25+P25+R25+T25+V25))
A26: 12 | B26: Long-term operational and maintenance arrangements | D26: =C26*C$8 | F26: =E26*E$8 | H26: =G26*G$8 | J26: =I26*I$8 | L26: =K26*K$8 | N26: =M26*M$8 | P26: =O26*O$8 | R26: =Q26*Q$8 | T26: =S26*S$8 | V26: =U26*U$8 | X26: =(SUM(W26+D26+F26+H26+J26+L26+N26+P26+R26+T26+V26))
A27: 13 | B27: Agreed maintenance schedule and cost apportionment | D27: =C27*C$8 | F27: =E27*E$8 | H27: =G27*G$8 | J27: =I27*I$8 | L27: =K27*K$8 | N27: =M27*M$8 | P27: =O27*O$8 | R27: =Q27*Q$8 | T27: =S27*S$8 | V27: =U27*U$8 | X27: =(SUM(W27+D27+F27+H27+J27+L27+N27+P27+R27+T27+V27))
A28: 14 | B28: Lifecycle costing | D28: =C28*C$8 | F28: =E28*E$8 | H28: =G28*G$8 | J28: =I28*I$8 | L28: =K28*K$8 | N28: =M28*M$8 | P28: =O28*O$8 | R28: =Q28*Q$8 | T28: =S28*S$8 | V28: =U28*U$8 | X28: =(SUM(W28+D28+F28+H28+J28+L28+N28+P28+R28+T28+V28))
A29: 15 | B29: Inspection and monitoring protocols | D29: =C29*C$8 | F29: =E29*E$8 | H29: =G29*G$8 | J29: =I29*I$8 | L29: =K29*K$8 | N29: =M29*M$8 | P29: =O29*O$8 | R29: =Q29*Q$8 | T29: =S29*S$8 | V29: =U29*U$8 | X29: =(SUM(W29+D29+F29+H29+J29+L29+N29+P29+R29+T29+V29))
B30: Phase 3.2 – Drainage Asset Management Plan (CoGG approval) Subtotal | C30: =SUM(C24:C29) | D30: =SUM(D24:D29) | E30: =SUM(E24:E29) | F30: =SUM(F24:F29) | G30: =SUM(G24:G29) | H30: =SUM(H24:H29) | I30: =SUM(I24:I29) | J30: =SUM(J24:J29) | ... X30: =SUM(X24:X29)
B31: Phase 3.3 – Integrated Water Management Plan (CoGG approval)
A32: 16 | B32: Review background studies relating to potable water reduction and stormwater volume reduction initiatives | D32: =C32*C$8 | F32: =E32*E$8 | H32: =G32*G$8 | J32: =I32*I$8 | L32: =K32*K$8 | N32: =M32*M$8 | P32: =O32*O$8 | R32: =Q32*Q$8 | T32: =S32*S$8 | V32: =U32*U$8 | X32: =(SUM(W32+D32+F32+H32+J32+L32+N32+P32+R32+T32+V32))
A33: 17 | B33: Establish stormwater volume reduction targets (informed in part by the EIA) | D33: =C33*C$8 | F33: =E33*E$8 | H33: =G33*G$8 | J33: =I33*I$8 | L33: =K33*K$8 | N33: =M33*M$8 | P33: =O33*O$8 | R33: =Q33*Q$8 | T33: =S33*S$8 | V33: =U33*U$8 | X33: =(SUM(W33+D33+F33+H33+J33+L33+N33+P33+R33+T33+V33))
A34: 18 | B34: Qualitative analysis of IWM 'long list' through the lens of volume reduction at lot, precinct, and regional scale | D34: =C34*C$8 | F34: =E34*E$8 | H34: =G34*G$8 | J34: =I34*I$8 | L34: =K34*K$8 | N34: =M34*M$8 | P34: =O34*O$8 | R34: =Q34*Q$8 | T34: =S34*S$8 | V34: =U34*U$8 | X34: =(SUM(W34+D34+F34+H34+J34+L34+N34+P34+R34+T34+V34))
A35: 19 | B35: MUSIC modelling to quantify predicted volume reduction for each shortlist IWM option | D35: =C35*C$8 | F35: =E35*E$8 | H35: =G35*G$8 | J35: =I35*I$8 | L35: =K35*K$8 | N35: =M35*M$8 | P35: =O35*O$8 | R35: =Q35*Q$8 | T35: =S35*S$8 | V35: =U35*U$8 | X35: =(SUM(W35+D35+F35+H35+J35+L35+N35+P35+R35+T35+V35))
A36: 20 | B36: Refine 'long list' to 'short list' in consultation with Landowner Group and key stakeholders | D36: =C36*C$8 | F36: =E36*E$8 | H36: =G36*G$8 | J36: =I36*I$8 | L36: =K36*K$8 | N36: =M36*M$8 | P36: =O36*O$8 | R36: =Q36*Q$8 | T36: =S36*S$8 | V36: =U36*U$8 | X36: =(SUM(W36+D36+F36+H36+J36+L36+N36+P36+R36+T36+V36))
A37: 21 | B37: Determine preferred portfolio of options maximising IWM objectives and reaching volume reduction target | D37: =C37*C$8 | F37: =E37*E$8 | H37: =G37*G$8 | J37: =I37*I$8 | L37: =K37*K$8 | N37: =M37*M$8 | P37: =O37*O$8 | R37: =Q37*Q$8 | T37: =S37*S$8 | V37: =U37*U$8 | X37: =(SUM(W37+D37+F37+H37+J37+L37+N37+P37+R37+T37+V37))
A38: 22 | B38: Prepare high-level concept plan presenting selected IWM options | D38: =C38*C$8 | F38: =E38*E$8 | H38: =G38*G$8 | J38: =I38*I$8 | L38: =K38*K$8 | N38: =M38*M$8 | P38: =O38*O$8 | R38: =Q38*Q$8 | T38: =S38*S$8 | V38: =U38*U$8 | X38: =(SUM(W38+D38+F38+H38+J38+L38+N38+P38+R38+T38+V38))
A39: 23 | B39: Include IWM section in DSMS Report summarising options selection and volume reduction analysis | D39: =C39*C$8 | F39: =E39*E$8 | H39: =G39*G$8 | J39: =I39*I$8 | L39: =K39*K$8 | N39: =M39*M$8 | P39: =O39*O$8 | R39: =Q39*Q$8 | T39: =S39*S$8 | V39: =U39*U$8 | X39: =(SUM(W39+D39+F39+H39+J39+L39+N39+P39+R39+T39+V39))
A40: 24 | B40: Allowance for 3 × 2-hour stakeholder workshop meetings (Barwon Water, CoGG, CCMA, and other relevant stakeholders) to identify and present options | D40: =C40*C$8 | F40: =E40*E$8 | H40: =G40*G$8 | J40: =I40*I$8 | L40: =K40*K$8 | N40: =M40*M$8 | P40: =O40*O$8 | R40: =Q40*Q$8 | T40: =S40*S$8 | V40: =U40*U$8 | X40: =(SUM(W40+D40+F40+H40+J40+L40+N40+P40+R40+T40+V40))
B41: Phase 3.3 – Integrated Water Management Plan (CoGG approval) Subtotal | C41: =SUM(C32:C40) | D41: =SUM(D32:D40) | E41: =SUM(E32:E40) | F41: =SUM(F32:F40) | G41: =SUM(G32:G40) | H41: =SUM(H32:H40) | I41: =SUM(I32:I40) | J41: =SUM(J32:J40) | ... X41: =SUM(X32:X40)
B42: Phase 4 – Functional Design Plans and Report (CoGG approval)
A43: 25 | B43: Detailed hydraulic modelling | D43: =C43*C$8 | F43: =E43*E$8 | H43: =G43*G$8 | J43: =I43*I$8 | L43: =K43*K$8 | N43: =M43*M$8 | P43: =O43*O$8 | R43: =Q43*Q$8 | T43: =S43*S$8 | V43: =U43*U$8 | X43: =(SUM(W43+D43+F43+H43+J43+L43+N43+P43+R43+T43+V43))
A44: 26 | B44: Functional design of drainage infrastructure | D44: =C44*C$8 | F44: =E44*E$8 | H44: =G44*G$8 | J44: =I44*I$8 | L44: =K44*K$8 | N44: =M44*M$8 | P44: =O44*O$8 | R44: =Q44*Q$8 | T44: =S44*S$8 | V44: =U44*U$8 | X44: =(SUM(W44+D44+F44+H44+J44+L44+N44+P44+R44+T44+V44))
A45: 27 | B45: Basin design | D45: =C45*C$8 | F45: =E45*E$8 | H45: =G45*G$8 | J45: =I45*I$8 | L45: =K45*K$8 | N45: =M45*M$8 | P45: =O45*O$8 | R45: =Q45*Q$8 | T45: =S45*S$8 | V45: =U45*U$8 | X45: =(SUM(W45+D45+F45+H45+J45+L45+N45+P45+R45+T45+V45))
A46: 28 | B46: Integration with upstream and downstream systems | D46: =C46*C$8 | F46: =E46*E$8 | H46: =G46*G$8 | J46: =I46*I$8 | L46: =K46*K$8 | N46: =M46*M$8 | P46: =O46*O$8 | R46: =Q46*Q$8 | T46: =S46*S$8 | V46: =U46*U$8 | X46: =(SUM(W46+D46+F46+H46+J46+L46+N46+P46+R46+T46+V46))
A47: 29 | B47: Functional Design Report with CAD drawings suitable for CoGG approval | D47: =C47*C$8 | F47: =E47*E$8 | H47: =G47*G$8 | J47: =I47*I$8 | L47: =K47*K$8 | N47: =M47*M$8 | P47: =O47*O$8 | R47: =Q47*Q$8 | T47: =S47*S$8 | V47: =U47*U$8 | X47: =(SUM(W47+D47+F47+H47+J47+L47+N47+P47+R47+T47+V47))
B48: Phase 4 – Functional Design Plans and Report (CoGG approval) Subtotal | C48: =SUM(C43:C47) | D48: =SUM(D43:D47) | E48: =SUM(E43:E47) | F48: =SUM(F43:F47) | G48: =SUM(G43:G47) | H48: =SUM(H43:H47) | I48: =SUM(I43:I47) | J48: =SUM(J43:J47) | ... X48: =SUM(X43:X47)
B49: Phase 5.1 – Asset Costing (Provisional)
A50: 30 | B50: Detailed asset cost estimate covering drainage and stormwater infrastructure designed under Phase 4 | D50: =C50*C$8 | F50: =E50*E$8 | H50: =G50*G$8 | J50: =I50*I$8 | L50: =K50*K$8 | N50: =M50*M$8 | P50: =O50*O$8 | R50: =Q50*Q$8 | T50: =S50*S$8 | V50: =U50*U$8 | X50: =(SUM(W50+D50+F50+H50+J50+L50+N50+P50+R50+T50+V50))
A51: 31 | B51: Cost estimate to support landowner contribution apportionment, ICP/DCP submissions, and reimbursement claims with the relevant drainage authority | D51: =C51*C$8 | F51: =E51*E$8 | H51: =G51*G$8 | J51: =I51*I$8 | L51: =K51*K$8 | N51: =M51*M$8 | P51: =O51*O$8 | R51: =Q51*Q$8 | T51: =S51*S$8 | V51: =U51*U$8 | X51: =(SUM(W51+D51+F51+H51+J51+L51+N51+P51+R51+T51+V51))
A52: 32 | B52: Fee calculated as a percentage of estimated construction cost per ACEA sliding scale | D52: =C52*C$8 | F52: =E52*E$8 | H52: =G52*G$8 | J52: =I52*I$8 | L52: =K52*K$8 | N52: =M52*M$8 | P52: =O52*O$8 | R52: =Q52*Q$8 | T52: =S52*S$8 | V52: =U52*U$8 | X52: =(SUM(W52+D52+F52+H52+J52+L52+N52+P52+R52+T52+V52))
B53: Phase 5.1 – Asset Costing (Provisional) Subtotal | C53: =SUM(C50:C52) | D53: =SUM(D50:D52) | E53: =SUM(E50:E52) | F53: =SUM(F50:F52) | G53: =SUM(G50:G52) | H53: =SUM(H50:H52) | I53: =SUM(I50:I52) | J53: =SUM(J50:J52) | ... X53: =SUM(X50:X52)
B54: Phase 5.2 – Ongoing Technical Advice (as required, T&M)
A55: 33 | B55: Response to referral authority comments and conditions (CCMA, CoGG) | D55: =C55*C$8 | F55: =E55*E$8 | H55: =G55*G$8 | J55: =I55*I$8 | L55: =K55*K$8 | N55: =M55*M$8 | P55: =O55*O$8 | R55: =Q55*Q$8 | T55: =S55*S$8 | V55: =U55*U$8 | X55: =(SUM(W55+D55+F55+H55+J55+L55+N55+P55+R55+T55+V55))
A56: 34 | B56: Technical submission responses | D56: =C56*C$8 | F56: =E56*E$8 | H56: =G56*G$8 | J56: =I56*I$8 | L56: =K56*K$8 | N56: =M56*M$8 | P56: =O56*O$8 | R56: =Q56*Q$8 | T56: =S56*S$8 | V56: =U56*U$8 | X56: =(SUM(W56+D56+F56+H56+J56+L56+N56+P56+R56+T56+V56))
A57: 35 | B57: Resolution of issues | D57: =C57*C$8 | F57: =E57*E$8 | H57: =G57*G$8 | J57: =I57*I$8 | L57: =K57*K$8 | N57: =M57*M$8 | P57: =O57*O$8 | R57: =Q57*Q$8 | T57: =S57*S$8 | V57: =U57*U$8 | X57: =(SUM(W57+D57+F57+H57+J57+L57+N57+P57+R57+T57+V57))
A58: 36 | B58: Interdisciplinary coordination | D58: =C58*C$8 | F58: =E58*E$8 | H58: =G58*G$8 | J58: =I58*I$8 | L58: =K58*K$8 | N58: =M58*M$8 | P58: =O58*O$8 | R58: =Q58*Q$8 | T58: =S58*S$8 | V58: =U58*U$8 | X58: =(SUM(W58+D58+F58+H58+J58+L58+N58+P58+R58+T58+V58))
A59: 37 | B59: Supplementary studies as identified by authorities (additional scope beyond allowance quoted separately) | D59: =C59*C$8 | F59: =E59*E$8 | H59: =G59*G$8 | J59: =I59*I$8 | L59: =K59*K$8 | N59: =M59*M$8 | P59: =O59*O$8 | R59: =Q59*Q$8 | T59: =S59*S$8 | V59: =U59*U$8 | X59: =(SUM(W59+D59+F59+H59+J59+L59+N59+P59+R59+T59+V59))
B60: Phase 5.2 – Ongoing Technical Advice (as required, T&M) Subtotal | C60: =SUM(C55:C59) | D60: =SUM(D55:D59) | E60: =SUM(E55:E59) | F60: =SUM(F55:F59) | G60: =SUM(G55:G59) | H60: =SUM(H55:H59) | I60: =SUM(I55:I59) | J60: =SUM(J55:J59) | ... X60: =SUM(X55:X59)
B61: Total (Exc. GST) | X61: =X22+X30+X41+X48+X53+X60
B68: Variation 1
A69: Task | C69: 400 | E69: 400 | G69: 400 | I69: 320 | K69: 320 | M69: 250 | O69: 220 | Q69: 180 | S69: 180 | U69: 200 | W69: Expenses | X69: Sub Totals
C70: Rianda Mills | E70: Luke Cunningham | G70: Jessica Ward | I70: Maria McCrann | K70: Milan Wickramarachchi | M70: Amin Zarrin | O70: Samantha Nieves | Q70: Emily Felstead | S70: Holly Edmunds | U70: Danni Bailey
C71: Director & Principal Engineer | E71: Director & Principal Engineer | G71: Hydrologist and Technician | I71: Senior Engineer | K71: Senior Engineer | M71: Project Engineer | O71: Graduate Scientist | Q71: Graduate Engineer | S71: Executive Assistant | U71: Operations Coordinator
A72: Item | B72: Description | C72: Hours | D72: Fee (Exc. GST) | E72: Hours | F72: Fee (Exc. GST) | G72: Hours | H72: Fee (Exc. GST) | I72: Hours | J72: Fee (Exc. GST) | K72: Hours | L72: Fee (Exc. GST) | M72: Hours | N72: Fee (Exc. GST) | O72: Hours | P72: Fee (Exc. GST) | Q72: Hours | R72: Fee (Exc. GST) | S72: Hours | T72: Fee (Exc. GST) | U72: Hours | V72: Fee (Exc. GST) | W72: Fee (Exc. GST) | X72: Exc. GST
A73: 1 | B73: INSERT TASK HERE | D73: =C73*C$8 | F73: =E73*E$8 | H73: =G73*G$8 | J73: =I73*I$8 | L73: =K73*K$8 | N73: =M73*M$8 | P73: =O73*O$8 | R73: =Q73*Q$8 | T73: =S73*S$8 | V73: =U73*U$8 | X73: =(SUM(W73+P73+F73+N73+D73+T73+L73+R73+V73+J73))
A74: 2 | D74: =C74*C$8 | F74: =E74*E$8 | H74: =G74*G$8 | J74: =I74*I$8 | L74: =K74*K$8 | N74: =M74*M$8 | P74: =O74*O$8 | R74: =Q74*Q$8 | T74: =S74*S$8 | V74: =U74*U$8 | X74: =(SUM(W74+P74+F74+N74+D74+T74+L74+R74+V74+J74))
A75: 3 | D75: =C75*C$8 | F75: =E75*E$8 | H75: =G75*G$8 | J75: =I75*I$8 | L75: =K75*K$8 | N75: =M75*M$8 | P75: =O75*O$8 | R75: =Q75*Q$8 | T75: =S75*S$8 | V75: =U75*U$8 | X75: =(SUM(W75+P75+F75+N75+D75+T75+L75+R75+V75+J75))
A76: 4 | D76: =C76*C$8 | F76: =E76*E$8 | H76: =G76*G$8 | J76: =I76*I$8 | L76: =K76*K$8 | N76: =M76*M$8 | P76: =O76*O$8 | R76: =Q76*Q$8 | T76: =S76*S$8 | V76: =U76*U$8 | X76: =(SUM(W76+P76+F76+N76+D76+T76+L76+R76+V76+J76))
A77: 5 | D77: =C77*C$8 | F77: =E77*E$8 | H77: =G77*G$8 | J77: =I77*I$8 | L77: =K77*K$8 | N77: =M77*M$8 | P77: =O77*O$8 | R77: =Q77*Q$8 | T77: =S77*S$8 | V77: =U77*U$8 | X77: =(SUM(W77+P77+F77+N77+D77+T77+L77+R77+V77+J77))
B78: Sub Total | C78: =SUM(C35:C39) | D78: =SUM(D35:D39) | E78: =SUM(E35:E39) | F78: =SUM(F35:F39) | G78: =SUM(G35:G39) | H78: =SUM(H35:H39) | I78: =SUM(I35:I39) | J78: =SUM(J35:J39) | ... V78: =SUM(V35:V39) | W78: =SUM(W35:W35)
B79: Total (Exc. GST) | X79: =SUM(X35:X39)

Sheet Invoicing
A1: Rain Invoice Tracker
A4: Task | C4: Sub Totals | D4: <insert month> | F4: <insert month> | H4: <insert month> | J4: <insert month> | L4: <insert month> | N4: <insert month> | R4: Invoiced to date
A7: Item | B7: Description | C7: Exc. GST | D7: % complete | E7: Invoice total | F7: % complete | G7: Invoice total | H7: % complete | I7: Invoice total | J7: % complete | K7: Invoice total | L7: % complete | M7: Invoice total | N7: % complete | O7: Invoice total | R7: % complete | S7: Invoice total | U7: Remaining Fee
A8: ='Rain Fee'!A12 | B8: ='Rain Fee'!B12 | C8: ='Rain Fee'!X12 | E8: =+C8*(D8) | G8: =+C8*(F8) | I8: =+E8*(H8) | K8: =+G8*(J8) | M8: =+I8*(L8) | O8: =+K8*(N8) | R8: =D8+F8+H8+J8+L8+N8 | S8: =E8+G8+I8+K8+M8+O8 | U8: =C8-S8
A9: ='Rain Fee'!A13 | B9: ='Rain Fee'!B13 | C9: ='Rain Fee'!X13 | E9: =+C9*(D9) | G9: =+C9*(F9) | I9: =+E9*(H9) | K9: =+G9*(J9) | M9: =+I9*(L9) | O9: =+K9*(N9) | R9: =D9+F9+H9+J9+L9+N9 | S9: =E9+G9+I9+K9+M9+O9 | U9: =C9-S9
A10: ='Rain Fee'!A14 | B10: ='Rain Fee'!B14 | C10: ='Rain Fee'!X14 | E10: =+C10*(D10) | G10: =+C10*(F10) | I10: =+E10*(H10) | K10: =+G10*(J10) | M10: =+I10*(L10) | O10: =+K10*(N10) | R10: =D10+F10+H10+J10+L10+N10 | S10: =E10+G10+I10+K10+M10+O10 | U10: =C10-S10
A11: ='Rain Fee'!A15 | B11: ='Rain Fee'!B15 | C11: ='Rain Fee'!X15 | E11: =+C11*(D11) | G11: =+C11*(F11) | I11: =+E11*(H11) | K11: =+G11*(J11) | M11: =+I11*(L11) | O11: =+K11*(N11) | R11: =D11+F11+H11+J11+L11+N11 | S11: =E11+G11+I11+K11+M11+O11 | U11: =C11-S11
A12: ='Rain Fee'!A16 | B12: ='Rain Fee'!B16 | C12: ='Rain Fee'!X16 | E12: =+C12*(D12) | G12: =+C12*(F12) | I12: =+E12*(H12) | K12: =+G12*(J12) | M12: =+I12*(L12) | O12: =+K12*(N12) | R12: =D12+F12+H12+J12+L12+N12 | S12: =E12+G12+I12+K12+M12+O12 | U12: =C12-S12
A13: ='Rain Fee'!A17 | B13: ='Rain Fee'!B17 | C13: ='Rain Fee'!X17 | E13: =+C13*(D13) | G13: =+C13*(F13) | I13: =+E13*(H13) | K13: =+G13*(J13) | M13: =+I13*(L13) | O13: =+K13*(N13) | R13: =D13+F13+H13+J13+L13+N13 | S13: =E13+G13+I13+K13+M13+O13 | U13: =C13-S13
A14: ='Rain Fee'!A18 | B14: ='Rain Fee'!B18 | C14: ='Rain Fee'!X18 | E14: =+C14*(D14) | G14: =+C14*(F14) | I14: =+E14*(H14) | K14: =+G14*(J14) | M14: =+I14*(L14) | O14: =+K14*(N14) | R14: =D14+F14+H14+J14+L14+N14 | S14: =E14+G14+I14+K14+M14+O14 | U14: =C14-S14
A15: ='Rain Fee'!A19 | B15: ='Rain Fee'!B19 | C15: ='Rain Fee'!X19 | E15: =+C15*(D15) | G15: =+C15*(F15) | I15: =+E15*(H15) | K15: =+G15*(J15) | M15: =+I15*(L15) | O15: =+K15*(N15) | R15: =D15+F15+H15+J15+L15+N15 | S15: =E15+G15+I15+K15+M15+O15 | U15: =C15-S15
A16: ='Rain Fee'!A20 | B16: ='Rain Fee'!B20 | C16: ='Rain Fee'!X20 | E16: =+C16*(D16) | G16: =+C16*(F16) | I16: =+E16*(H16) | K16: =+G16*(J16) | M16: =+I16*(L16) | O16: =+K16*(N16) | R16: =D16+F16+H16+J16+L16+N16 | S16: =E16+G16+I16+K16+M16+O16 | U16: =C16-S16
A17: ='Rain Fee'!A21 | B17: ='Rain Fee'!B21 | C17: ='Rain Fee'!X21 | E17: =+C17*(D17) | G17: =+C17*(F17) | I17: =+E17*(H17) | K17: =+G17*(J17) | M17: =+I17*(L17) | O17: =+K17*(N17) | R17: =D17+F17+H17+J17+L17+N17 | S17: =E17+G17+I17+K17+M17+O17 | U17: =C17-S17
B18: Total (Exc. GST) | C18: ='Rain Fee'!X23 | D18: Invoice total | E18: =SUM(E8:E17) | F18: Invoice total | G18: =SUM(G8:G17) | H18: Invoice total | I18: =SUM(I8:I17) | J18: Invoice total | K18: =SUM(K8:K17) | L18: Invoice total | M18: =SUM(M8:M17) | N18: Invoice total | O18: =SUM(O8:O17) | R18: Invoice total | S18: =SUM(S8:S17)
B22: Variation 1
A23: Task | C23: Sub Totals | D23: <Insert Month> | F23: <Insert Month> | H23: <Insert Month> | J23: <Insert Month> | L23: <Insert Month> | N23: <Insert Month> | R23: Invoiced to date
A26: Item | B26: Description | C26: Exc. GST | D26: % complete | E26: Invoice total | F26: % complete | G26: Invoice total | H26: % complete | I26: Invoice total | J26: % complete | K26: Invoice total | L26: % complete | M26: Invoice total | N26: % complete | O26: Invoice total | R26: % complete | S26: Invoice total
A27: ='Rain Fee'!A35 | B27: ='Rain Fee'!B35 | C27: ='Rain Fee'!X35 | E27: =+C27*(D27) | G27: =+E27*(F27) | I27: =+G27*(H27) | K27: =+I27*(J27) | M27: =+K27*(L27) | O27: =+M27*(N27) | R27: =D27+F27+H27+J27+L27+N27 | S27: =E27+G27+I27+K27+M27+O27
A28: ='Rain Fee'!A36 | B28: ='Rain Fee'!B36 | C28: ='Rain Fee'!X36 | E28: =+C28*(D28) | G28: =+E28*(F28) | I28: =+G28*(H28) | K28: =+I28*(J28) | M28: =+K28*(L28) | O28: =+M28*(N28) | R28: =D28+F28+H28+J28+L28+N28 | S28: =E28+G28+I28+K28+M28+O28
A29: ='Rain Fee'!A37 | B29: ='Rain Fee'!B37 | C29: ='Rain Fee'!X37 | E29: =+C29*(D29) | G29: =+E29*(F29) | I29: =+G29*(H29) | K29: =+I29*(J29) | M29: =+K29*(L29) | O29: =+M29*(N29) | R29: =D29+F29+H29+J29+L29+N29 | S29: =E29+G29+I29+K29+M29+O29
A30: ='Rain Fee'!A38 | B30: ='Rain Fee'!B38 | C30: ='Rain Fee'!X38 | E30: =+C30*(D30) | G30: =+E30*(F30) | I30: =+G30*(H30) | K30: =+I30*(J30) | M30: =+K30*(L30) | O30: =+M30*(N30) | R30: =D30+F30+H30+J30+L30+N30 | S30: =E30+G30+I30+K30+M30+O30
A31: ='Rain Fee'!A39 | B31: ='Rain Fee'!B39 | C31: ='Rain Fee'!X39 | E31: =+C31*(D31) | G31: =+E31*(F31) | I31: =+G31*(H31) | K31: =+I31*(J31) | M31: =+K31*(L31) | O31: =+M31*(N31) | R31: =D31+F31+H31+J31+L31+N31 | S31: =E31+G31+I31+K31+M31+O31
B32: Total (Exc. GST) | C32: ='Rain Fee'!X41 | D32: Invoice total | E32: =SUM(E27:E31) | F32: Invoice total | G32: =SUM(G27:G31) | H32: Invoice total | I32: =SUM(I27:I31) | J32: Invoice total | K32: =SUM(K27:K31) | L32: Invoice total | M32: =SUM(M27:M31) | N32: Invoice total | O32: =SUM(O27:O31) | R32: Invoice total | S32: =SUM(S27:S31)

Sheet Sub-Consultant
B1: Consultant:
A3: Tasks | C3: Fee | D3: Invoice # | E3: Invoice # | F3: Invoice #
A4: Item | B4: Description
A5: 1
A6: 2
A7: 3
A8: 4
B9: Total | C9: =SUM(C4:C8) | D9: =SUM(D4:D8) | E9: =SUM(E4:E8) | F9: =SUM(F4:F8)
